ply_bibtex_parser/__init__.py
ply_bibtex_parser/lexer.py
ply_bibtex_parser/models.py
ply_bibtex_parser/parser.py
ply_bibtex_parser-0.1.0.dist-info/LICENSE
ply_bibtex_parser-0.1.0.dist-info/WHEEL
ply_bibtex_parser-0.1.0.dist-info/METADATA
ply_bibtex_parser-0.1.0.dist-info/RECORD
