Metadata-Version: 2.1
Name: ply-bibtex-parser
Version: 0.1.0
Summary: A simple ply-based parser for BibTeX
Home-page: https://github.com/micahjsmith/ply-bibtex-parser
License: MIT
Keywords: ply,parser,bibtex
Author: Micah Smith
Author-email: micahjsmith@gmail.com
Requires-Python: >=3.6,<4.0
Classifier: Development Status :: 2 - Pre-Alpha
Classifier: Environment :: Console
Classifier: Intended Audience :: Developers
Classifier: License :: OSI Approved :: MIT License
Classifier: Operating System :: OS Independent
Classifier: Programming Language :: Python
Classifier: Programming Language :: Python :: 3
Classifier: Programming Language :: Python :: 3 :: Only
Classifier: Programming Language :: Python :: 3.6
Classifier: Programming Language :: Python :: 3.7
Classifier: Programming Language :: Python :: 3.8
Classifier: Programming Language :: Python :: 3.9
Classifier: Topic :: Software Development :: Libraries :: Python Modules
Requires-Dist: ply (>=3.11,<4.0)
Project-URL: Repository, https://github.com/micahjsmith/ply-bibtex-parser
